inventree_common_data/__init__.py
inventree_common_data/datastructures.py
inventree_common_data/inventree_common_data.py
inventree_common_data/sources/3166-1/4e13b495-5da3-48fd-86cd-aad239c1b570_v1.0.0_3166-1.yaml
inventree_common_data/sources/ral/46821d3d-cd7e-4b39-b631-4c29ffc29107_v1.0.0_ral.yaml
inventree_common_data/sources/ral/46821d3d-cd7e-4b39-b631-4c29ffc29107_v1.1.0_ral.yaml
inventree_common_data/sources/ral/46821d3d-cd7e-4b39-b631-4c29ffc29107_v1.2.0_ral.yaml
inventree_common_data/static/ui_settings.js
inventree_common_data-0.3.5.dist-info/METADATA
inventree_common_data-0.3.5.dist-info/WHEEL
inventree_common_data-0.3.5.dist-info/entry_points.txt
inventree_common_data-0.3.5.dist-info/top_level.txt
inventree_common_data-0.3.5.dist-info/RECORD
