Metadata-Version: 2.4
Name: inventree-common-data
Version: 0.3.5
Summary: Selection Data for common use cases
Author-email: Matthias Mair <code@mjmair.com>
License-Expression: LicenseRef-Invenhost-Closed
Project-URL: Repository, https://github.com/invenhost/inventree-common-data
Project-URL: Issues, https://github.com/invenhost/inventree-common-data/issues
Project-URL: Changelog, https://github.com/invenhost/inventree-common-data/blob/main/CHANGELOG.md
Project-URL: Funding, https://polar.sh/invenhost
Keywords: inventree,inventree-plugin,inventree-common-data
Classifier: Programming Language :: Python :: 3
Classifier: Operating System :: OS Independent
Classifier: Development Status :: 5 - Production/Stable
Classifier: Environment :: Plugins
Classifier: Framework :: Django
Classifier: Intended Audience :: Developers
Classifier: Intended Audience :: Manufacturing
Classifier: Intended Audience :: End Users/Desktop
Classifier: Topic :: Scientific/Engineering
Classifier: Framework :: InvenTree
Requires-Python: >=3.9
Requires-Dist: django
Requires-Dist: pydantic>=2.9.1
Requires-Dist: inventree-server<2,~=0.18.0dev0
Provides-Extra: dev
Requires-Dist: twine; extra == "dev"
Requires-Dist: setuptools; extra == "dev"
